spinchimp
