Metadata-Version: 1.1
Name: spinchimp
Version: 0.1.1
Summary: Python bindings for SpinChimp API
Home-page: http://www.niteoweb.com
Author: NiteoWeb Ltd.
Author-email: info@niteoweb.com
License: BSD
Keywords: API spinner SpinChimp
Platform: UNKNOWN
Classifier: Programming Language :: Python
Classifier: Topic :: Internet :: WWW/HTTP
